dummy.cpython-310-x86_64-linux-gnu.so
dead_instrumenter/__init__.py
dead_instrumenter/instrumenter.py
dead_instrumenter/dead-instrument
dead_instrumenter/py.typed
test/__init__.py
test/vr_instrumenter_test.py
test/utils.py
test/preprocessing_test.py
test/dce_instrumenter_test.py
dead_instrumenter-0.3.3.dist-info/WHEEL
dead_instrumenter-0.3.3.dist-info/METADATA
dead_instrumenter-0.3.3.dist-info/RECORD
dead_instrumenter-0.3.3.dist-info/LICENSE
dead_instrumenter-0.3.3.dist-info/top_level.txt
