Metadata-Version: 2.1
Name: dead-instrumenter
Version: 0.3.3
Summary: A C/C++ code instrumenter used in DEAD
Home-page: https://github.com/DeadCodeProductions/dead_instrumenter
Author: Theodoros Theodoridis
Author-email: theodort@inf.ethz.ch
License: Apache License 2.0
Classifier: Programming Language :: Python :: 3
Requires-Python: >=3.10
License-File: LICENSE
Requires-Dist: diopter (>=0.0.11)
